dumbcpm/__main__.py
dumbcpm-0.3.6.dist-info/LICENSE.txt
dumbcpm-0.3.6.dist-info/METADATA
dumbcpm-0.3.6.dist-info/WHEEL
dumbcpm-0.3.6.dist-info/top_level.txt
dumbcpm-0.3.6.dist-info/RECORD
